dynashell/__init__.py
dynashell/check.py
dynashell/classes.py
dynashell/const.py
dynashell/main.py
dynashell/setting.yaml
dynashell/utils.py
dynashell-0.1.7.dist-info/licenses/LICENSE
dynashell-0.1.7.dist-info/METADATA
dynashell-0.1.7.dist-info/WHEEL
dynashell-0.1.7.dist-info/top_level.txt
dynashell-0.1.7.dist-info/RECORD
