Metadata-Version: 2.4
Name: dynashell
Version: 0.1.7
Summary: A flexible shell to run python snippets in a configurable context
Author: Ralph Boots
License-Expression: GPL-3.0-or-later
Project-URL: Homepage, https://github.com/rtboots/dynashell
Classifier: Programming Language :: Python :: 3
Classifier: Operating System :: OS Independent
Requires-Python: >=3.10
License-File: LICENSE
Requires-Dist: PyYAML
Dynamic: license-file
